<annotation>
  <folder>DJI</folder>
  <filename>DJI_20240518124325_0048_V234.jpg</filename>
  <source>
    <database>Unknown</database>
    <annotation>Unknown</annotation>
    <image>Unknown</image>
  </source>
  <size>
    <width>256</width>
    <height>256</height>
    <depth></depth>
  </size>
  <segmented>0</segmented>
  <object>
    <name>waste</name>
    <truncated>0</truncated>
    <occluded>0</occluded>
    <difficult>0</difficult>
    <bndbox>
      <xmin>96.09</xmin>
      <ymin>105.46</ymin>
      <xmax>106.49</xmax>
      <ymax>120.86</ymax>
    </bndbox>
    <attributes>
      <attribute>
        <name>rotation</name>
        <value>0.0</value>
      </attribute>
    </attributes>
  </object>
  <object>
    <name>waste</name>
    <truncated>0</truncated>
    <occluded>0</occluded>
    <difficult>0</difficult>
    <bndbox>
      <xmin>216.24</xmin>
      <ymin>121.1</ymin>
      <xmax>224.32</xmax>
      <ymax>124.0</ymax>
    </bndbox>
    <attributes>
      <attribute>
        <name>rotation</name>
        <value>0.0</value>
      </attribute>
    </attributes>
  </object>
  <object>
    <name>waste</name>
    <truncated>0</truncated>
    <occluded>0</occluded>
    <difficult>0</difficult>
    <bndbox>
      <xmin>165.87</xmin>
      <ymin>203.48</ymin>
      <xmax>168.97</xmax>
      <ymax>209.08</ymax>
    </bndbox>
    <attributes>
      <attribute>
        <name>rotation</name>
        <value>0.0</value>
      </attribute>
    </attributes>
  </object>
  <object>
    <name>waste</name>
    <truncated>0</truncated>
    <occluded>0</occluded>
    <difficult>0</difficult>
    <bndbox>
      <xmin>212.09</xmin>
      <ymin>89.35</ymin>
      <xmax>230.75</xmax>
      <ymax>92.9</ymax>
    </bndbox>
    <attributes>
      <attribute>
        <name>rotation</name>
        <value>0.0</value>
      </attribute>
    </attributes>
  </object>
  <object>
    <name>waste</name>
    <truncated>0</truncated>
    <occluded>0</occluded>
    <difficult>0</difficult>
    <bndbox>
      <xmin>248.58</xmin>
      <ymin>21.36</ymin>
      <xmax>254.83</xmax>
      <ymax>31.93</ymax>
    </bndbox>
    <attributes>
      <attribute>
        <name>rotation</name>
        <value>0.0</value>
      </attribute>
    </attributes>
  </object>
  <object>
    <name>waste</name>
    <truncated>0</truncated>
    <occluded>0</occluded>
    <difficult>0</difficult>
    <bndbox>
      <xmin>248.79</xmin>
      <ymin>66.56</ymin>
      <xmax>252.52</xmax>
      <ymax>76.1</ymax>
    </bndbox>
    <attributes>
      <attribute>
        <name>rotation</name>
        <value>0.0</value>
      </attribute>
    </attributes>
  </object>
  <object>
    <name>waste</name>
    <truncated>0</truncated>
    <occluded>0</occluded>
    <difficult>0</difficult>
    <bndbox>
      <xmin>83.79</xmin>
      <ymin>115.06</ymin>
      <xmax>88.89</xmax>
      <ymax>129.66</ymax>
    </bndbox>
    <attributes>
      <attribute>
        <name>rotation</name>
        <value>0.0</value>
      </attribute>
    </attributes>
  </object>
  <object>
    <name>waste</name>
    <truncated>0</truncated>
    <occluded>0</occluded>
    <difficult>0</difficult>
    <bndbox>
      <xmin>190.57</xmin>
      <ymin>177.98</ymin>
      <xmax>192.67</xmax>
      <ymax>187.88</ymax>
    </bndbox>
    <attributes>
      <attribute>
        <name>rotation</name>
        <value>0.0</value>
      </attribute>
    </attributes>
  </object>
  <object>
    <name>waste</name>
    <truncated>0</truncated>
    <occluded>0</occluded>
    <difficult>0</difficult>
    <bndbox>
      <xmin>196.74</xmin>
      <ymin>115.09</ymin>
      <xmax>199.44</xmax>
      <ymax>125.66</ymax>
    </bndbox>
    <attributes>
      <attribute>
        <name>rotation</name>
        <value>0.0</value>
      </attribute>
    </attributes>
  </object>
  <object>
    <name>waste</name>
    <truncated>0</truncated>
    <occluded>0</occluded>
    <difficult>0</difficult>
    <bndbox>
      <xmin>199.65</xmin>
      <ymin>101.4</ymin>
      <xmax>222.9</xmax>
      <ymax>115.71</ymax>
    </bndbox>
    <attributes>
      <attribute>
        <name>rotation</name>
        <value>0.0</value>
      </attribute>
    </attributes>
  </object>
  <object>
    <name>waste</name>
    <truncated>0</truncated>
    <occluded>0</occluded>
    <difficult>0</difficult>
    <bndbox>
      <xmin>170.94</xmin>
      <ymin>170.04</ymin>
      <xmax>189.83</xmax>
      <ymax>184.39</ymax>
    </bndbox>
    <attributes>
      <attribute>
        <name>rotation</name>
        <value>348.50000000000006</value>
      </attribute>
    </attributes>
  </object>
  <object>
    <name>waste</name>
    <truncated>0</truncated>
    <occluded>0</occluded>
    <difficult>0</difficult>
    <bndbox>
      <xmin>159.34</xmin>
      <ymin>156.96</ymin>
      <xmax>182.7</xmax>
      <ymax>169.7</ymax>
    </bndbox>
    <attributes>
      <attribute>
        <name>rotation</name>
        <value>0.0</value>
      </attribute>
    </attributes>
  </object>
  <object>
    <name>waste</name>
    <truncated>0</truncated>
    <occluded>0</occluded>
    <difficult>0</difficult>
    <bndbox>
      <xmin>192.77</xmin>
      <ymin>189.78</ymin>
      <xmax>198.67</xmax>
      <ymax>193.68</ymax>
    </bndbox>
    <attributes>
      <attribute>
        <name>rotation</name>
        <value>0.0</value>
      </attribute>
    </attributes>
  </object>
  <object>
    <name>waste</name>
    <truncated>0</truncated>
    <occluded>0</occluded>
    <difficult>0</difficult>
    <bndbox>
      <xmin>192.67</xmin>
      <ymin>175.28</ymin>
      <xmax>199.57</xmax>
      <ymax>189.18</ymax>
    </bndbox>
    <attributes>
      <attribute>
        <name>rotation</name>
        <value>0.0</value>
      </attribute>
    </attributes>
  </object>
  <object>
    <name>waste</name>
    <truncated>0</truncated>
    <occluded>0</occluded>
    <difficult>0</difficult>
    <bndbox>
      <xmin>199.37</xmin>
      <ymin>174.58</ymin>
      <xmax>201.57</xmax>
      <ymax>185.18</ymax>
    </bndbox>
    <attributes>
      <attribute>
        <name>rotation</name>
        <value>0.0</value>
      </attribute>
    </attributes>
  </object>
  <object>
    <name>waste</name>
    <truncated>0</truncated>
    <occluded>0</occluded>
    <difficult>0</difficult>
    <bndbox>
      <xmin>83.09</xmin>
      <ymin>105.16</ymin>
      <xmax>88.89</xmax>
      <ymax>110.86</ymax>
    </bndbox>
    <attributes>
      <attribute>
        <name>rotation</name>
        <value>0.0</value>
      </attribute>
    </attributes>
  </object>
  <object>
    <name>waste</name>
    <truncated>0</truncated>
    <occluded>0</occluded>
    <difficult>0</difficult>
    <bndbox>
      <xmin>156.17</xmin>
      <ymin>209.48</ymin>
      <xmax>184.77</xmax>
      <ymax>214.48</ymax>
    </bndbox>
    <attributes>
      <attribute>
        <name>rotation</name>
        <value>0.0</value>
      </attribute>
    </attributes>
  </object>
  <object>
    <name>waste</name>
    <truncated>0</truncated>
    <occluded>0</occluded>
    <difficult>0</difficult>
    <bndbox>
      <xmin>169.27</xmin>
      <ymin>205.68</ymin>
      <xmax>173.47</xmax>
      <ymax>209.08</ymax>
    </bndbox>
    <attributes>
      <attribute>
        <name>rotation</name>
        <value>0.0</value>
      </attribute>
    </attributes>
  </object>
  <object>
    <name>waste</name>
    <truncated>0</truncated>
    <occluded>0</occluded>
    <difficult>0</difficult>
    <bndbox>
      <xmin>202.76</xmin>
      <ymin>93.09</ymin>
      <xmax>229.92</xmax>
      <ymax>101.19</ymax>
    </bndbox>
    <attributes>
      <attribute>
        <name>rotation</name>
        <value>0.0</value>
      </attribute>
    </attributes>
  </object>
  <object>
    <name>waste</name>
    <truncated>0</truncated>
    <occluded>0</occluded>
    <difficult>0</difficult>
    <bndbox>
      <xmin>221.63</xmin>
      <ymin>82.3</ymin>
      <xmax>230.96</xmax>
      <ymax>88.96</ymax>
    </bndbox>
    <attributes>
      <attribute>
        <name>rotation</name>
        <value>0.0</value>
      </attribute>
    </attributes>
  </object>
  <object>
    <name>waste</name>
    <truncated>0</truncated>
    <occluded>0</occluded>
    <difficult>0</difficult>
    <bndbox>
      <xmin>160.75</xmin>
      <ymin>137.48</ymin>
      <xmax>174.66</xmax>
      <ymax>143.68</ymax>
    </bndbox>
    <attributes>
      <attribute>
        <name>rotation</name>
        <value>0.0</value>
      </attribute>
    </attributes>
  </object>
  <object>
    <name>waste</name>
    <truncated>0</truncated>
    <occluded>0</occluded>
    <difficult>0</difficult>
    <bndbox>
      <xmin>164.75</xmin>
      <ymin>143.68</ymin>
      <xmax>170.66</xmax>
      <ymax>148.88</ymax>
    </bndbox>
    <attributes>
      <attribute>
        <name>rotation</name>
        <value>0.0</value>
      </attribute>
    </attributes>
  </object>
  <object>
    <name>waste</name>
    <truncated>0</truncated>
    <occluded>0</occluded>
    <difficult>0</difficult>
    <bndbox>
      <xmin>252.73</xmin>
      <ymin>59.1</ymin>
      <xmax>256.0</xmax>
      <ymax>74.44</ymax>
    </bndbox>
    <attributes>
      <attribute>
        <name>rotation</name>
        <value>0.0</value>
      </attribute>
    </attributes>
  </object>
  <object>
    <name>waste</name>
    <truncated>0</truncated>
    <occluded>0</occluded>
    <difficult>0</difficult>
    <bndbox>
      <xmin>166.66</xmin>
      <ymin>148.98</ymin>
      <xmax>170.85</xmax>
      <ymax>156.88</ymax>
    </bndbox>
    <attributes>
      <attribute>
        <name>rotation</name>
        <value>0.0</value>
      </attribute>
    </attributes>
  </object>
  <object>
    <name>waste</name>
    <truncated>0</truncated>
    <occluded>0</occluded>
    <difficult>0</difficult>
    <bndbox>
      <xmin>173.11</xmin>
      <ymin>185.61</ymin>
      <xmax>179.11</xmax>
      <ymax>192.89</ymax>
    </bndbox>
    <attributes>
      <attribute>
        <name>rotation</name>
        <value>349.69999999999993</value>
      </attribute>
    </attributes>
  </object>
  <object>
    <name>waste</name>
    <truncated>0</truncated>
    <occluded>0</occluded>
    <difficult>0</difficult>
    <bndbox>
      <xmin>160.45</xmin>
      <ymin>169.38</ymin>
      <xmax>169.66</xmax>
      <ymax>175.78</ymax>
    </bndbox>
    <attributes>
      <attribute>
        <name>rotation</name>
        <value>0.0</value>
      </attribute>
    </attributes>
  </object>
  <object>
    <name>waste</name>
    <truncated>0</truncated>
    <occluded>0</occluded>
    <difficult>0</difficult>
    <bndbox>
      <xmin>136.56</xmin>
      <ymin>180.24</ymin>
      <xmax>173.33</xmax>
      <ymax>206.05</ymax>
    </bndbox>
    <attributes>
      <attribute>
        <name>rotation</name>
        <value>348.50000000000006</value>
      </attribute>
    </attributes>
  </object>
  <object>
    <name>waste</name>
    <truncated>0</truncated>
    <occluded>0</occluded>
    <difficult>0</difficult>
    <bndbox>
      <xmin>127.57</xmin>
      <ymin>208.38</ymin>
      <xmax>139.07</xmax>
      <ymax>210.78</ymax>
    </bndbox>
    <attributes>
      <attribute>
        <name>rotation</name>
        <value>0.0</value>
      </attribute>
    </attributes>
  </object>
  <object>
    <name>waste</name>
    <truncated>0</truncated>
    <occluded>0</occluded>
    <difficult>0</difficult>
    <bndbox>
      <xmin>184.67</xmin>
      <ymin>207.08</ymin>
      <xmax>190.37</xmax>
      <ymax>212.08</ymax>
    </bndbox>
    <attributes>
      <attribute>
        <name>rotation</name>
        <value>0.0</value>
      </attribute>
    </attributes>
  </object>
  <object>
    <name>waste</name>
    <truncated>0</truncated>
    <occluded>0</occluded>
    <difficult>0</difficult>
    <bndbox>
      <xmin>200.06</xmin>
      <ymin>115.92</ymin>
      <xmax>209.81</xmax>
      <ymax>128.36</ymax>
    </bndbox>
    <attributes>
      <attribute>
        <name>rotation</name>
        <value>0.0</value>
      </attribute>
    </attributes>
  </object>
  <object>
    <name>waste</name>
    <truncated>0</truncated>
    <occluded>0</occluded>
    <difficult>0</difficult>
    <bndbox>
      <xmin>210.02</xmin>
      <ymin>116.33</ymin>
      <xmax>222.25</xmax>
      <ymax>120.89</ymax>
    </bndbox>
    <attributes>
      <attribute>
        <name>rotation</name>
        <value>0.0</value>
      </attribute>
    </attributes>
  </object>
  <object>
    <name>waste</name>
    <truncated>0</truncated>
    <occluded>0</occluded>
    <difficult>0</difficult>
    <bndbox>
      <xmin>222.66</xmin>
      <ymin>101.4</ymin>
      <xmax>228.47</xmax>
      <ymax>106.58</ymax>
    </bndbox>
    <attributes>
      <attribute>
        <name>rotation</name>
        <value>0.0</value>
      </attribute>
    </attributes>
  </object>
  <object>
    <name>waste</name>
    <truncated>0</truncated>
    <occluded>0</occluded>
    <difficult>0</difficult>
    <bndbox>
      <xmin>191.5</xmin>
      <ymin>193.9</ymin>
      <xmax>196.3</xmax>
      <ymax>196.4</ymax>
    </bndbox>
    <attributes>
      <attribute>
        <name>rotation</name>
        <value>0.0</value>
      </attribute>
    </attributes>
  </object>
  <object>
    <name>waste</name>
    <truncated>0</truncated>
    <occluded>0</occluded>
    <difficult>0</difficult>
    <bndbox>
      <xmin>88.99</xmin>
      <ymin>101.96</ymin>
      <xmax>96.19</xmax>
      <ymax>126.36</ymax>
    </bndbox>
    <attributes>
      <attribute>
        <name>rotation</name>
        <value>0.0</value>
      </attribute>
    </attributes>
  </object>
  <object>
    <name>waste</name>
    <truncated>0</truncated>
    <occluded>0</occluded>
    <difficult>0</difficult>
    <bndbox>
      <xmin>10.64</xmin>
      <ymin>95.0</ymin>
      <xmax>20.84</xmax>
      <ymax>101.22</ymax>
    </bndbox>
    <attributes>
      <attribute>
        <name>rotation</name>
        <value>15.100000000000009</value>
      </attribute>
    </attributes>
  </object>
  <object>
    <name>waste</name>
    <truncated>0</truncated>
    <occluded>0</occluded>
    <difficult>0</difficult>
    <bndbox>
      <xmin>236.76</xmin>
      <ymin>144.9</ymin>
      <xmax>247.75</xmax>
      <ymax>151.37</ymax>
    </bndbox>
    <attributes>
      <attribute>
        <name>rotation</name>
        <value>0.0</value>
      </attribute>
    </attributes>
  </object>
  <object>
    <name>waste</name>
    <truncated>0</truncated>
    <occluded>0</occluded>
    <difficult>0</difficult>
    <bndbox>
      <xmin>190.7</xmin>
      <ymin>196.68</ymin>
      <xmax>195.27</xmax>
      <ymax>200.28</ymax>
    </bndbox>
    <attributes>
      <attribute>
        <name>rotation</name>
        <value>0.0</value>
      </attribute>
    </attributes>
  </object>
</annotation>
