<annotation>
  <folder>DJI</folder>
  <filename>DJI_20240518124313_0039_V291.jpg</filename>
  <source>
    <database>Unknown</database>
    <annotation>Unknown</annotation>
    <image>Unknown</image>
  </source>
  <size>
    <width>256</width>
    <height>256</height>
    <depth></depth>
  </size>
  <segmented>0</segmented>
  <object>
    <name>waste</name>
    <truncated>0</truncated>
    <occluded>0</occluded>
    <difficult>0</difficult>
    <bndbox>
      <xmin>206.51</xmin>
      <ymin>208.77</ymin>
      <xmax>226.81</xmax>
      <ymax>220.8</ymax>
    </bndbox>
    <attributes>
      <attribute>
        <name>rotation</name>
        <value>348.1</value>
      </attribute>
    </attributes>
  </object>
  <object>
    <name>waste</name>
    <truncated>0</truncated>
    <occluded>0</occluded>
    <difficult>0</difficult>
    <bndbox>
      <xmin>200.66</xmin>
      <ymin>214.62</ymin>
      <xmax>206.47</xmax>
      <ymax>222.01</ymax>
    </bndbox>
    <attributes>
      <attribute>
        <name>rotation</name>
        <value>10.799999999999997</value>
      </attribute>
    </attributes>
  </object>
</annotation>
